dcapy/__init__.py
dcapy/auth/__init__.py
dcapy/auth/auth.py
dcapy/cashflow/__init__.py
dcapy/cashflow/cashflow.py
dcapy/console/__init__.py
dcapy/console/console.py
dcapy/dca/__init__.py
dcapy/dca/arps.py
dcapy/dca/dca.py
dcapy/dca/timeconverter.py
dcapy/dca/wor.py
dcapy/filters/__init__.py
dcapy/filters/filters.py
dcapy/schedule/__init__.py
dcapy/schedule/schedule.py
dcapy/wiener/__init__.py
dcapy/wiener/brownian.py
dcapy-0.1.14.dist-info/LICENSE
dcapy-0.1.14.dist-info/METADATA
dcapy-0.1.14.dist-info/WHEEL
dcapy-0.1.14.dist-info/RECORD
